test/__init__.py
test/test_cutprotocol.py
test/test_open_config.py
test/dataset/__init__.py
test/dataset/cutprotocol.py
test/dataset/open_config.py
yaml_config/__init__.py
yaml_config/configuration.py
yaml_config_reader-3.0.1.dist-info/LICENCE
yaml_config_reader-3.0.1.dist-info/METADATA
yaml_config_reader-3.0.1.dist-info/WHEEL
yaml_config_reader-3.0.1.dist-info/top_level.txt
yaml_config_reader-3.0.1.dist-info/RECORD
