Metadata-Version: 2.1
Name: yaml-config-reader
Version: 3.0.1
Summary: Package for reading configs from yml files
Home-page: https://github.com/J4CKVVH173/yaml-config
Author: J4CK VVH173, Polosha
Author-email: i78901234567890@gmail.com
Classifier: Programming Language :: Python :: 3
Classifier: License :: OSI Approved :: MIT License
Classifier: Operating System :: Unix
Classifier: Operating System :: Microsoft :: Windows
Requires-Python: >=3.8
License-File: LICENCE
Requires-Dist: PyYAML ==6.0.2
